deepview_torch/__init__.py
deepview_torch/_torch_producer.py
deepview_torch-3.9.6.dist-info/WHEEL
deepview_torch-3.9.6.dist-info/METADATA
deepview_torch-3.9.6.dist-info/RECORD
